ShapEV/EVsearch.py
ShapEV/__init__.py
ShapEV/funkit.py
ShapEV-0.0.1.dist-info/METADATA
ShapEV-0.0.1.dist-info/WHEEL
ShapEV-0.0.1.dist-info/entry_points.txt
ShapEV-0.0.1.dist-info/top_level.txt
ShapEV-0.0.1.dist-info/RECORD
