Metadata-Version: 2.1
Name: ShapEV
Version: 0.0.1
Summary: A package for identifying Equivalent Value based on joint SHAP values
Home-page: https://github.com/Bin-Cao/ShapEV
Author: Cao Bin
Author-email: bcao@shu.edu.com
Maintainer: Cao Bin
Maintainer-email: binjacobcao@gmail.com
License: MIT
Classifier: Development Status :: 3 - Alpha
Classifier: Intended Audience :: Developers
Classifier: Topic :: Software Development :: Libraries
Classifier: License :: OSI Approved :: MIT License
Classifier: Programming Language :: Python :: 3
Requires-Python: >=3.5
Requires-Dist: scikit-learn
